ahb_slave.v
module ahb_slave(
input HCLK,
input HRESETn,
input [31:0] HADDR,
input [31:0] HWDATA,
input HWRITE,
input HSEL,


output reg [31:0] HRDATA,
output reg HREADY


);


reg [31:0] memory [0:255];
integer i;
initial begin
    for (i=0;i<256 ;i=i+1 ) 
    memory[i] = 32'h0000000;
    
end

always @(posedge HCLK or negedge HRESETn) begin
    if (!HRESETn) begin
        HREADY <= 1;
        HRDATA <= 0;
    end else begin
        HREADY <= 1;

        if (HSEL) begin
            if (HWRITE)
                memory[HADDR[7:0]] <= HWDATA;
            else
                HRDATA <= memory[HADDR[7:0]];
        end
    end
end


endmodule

ahb_master.v
module ahb_master(
input HCLK,
input HRESETn,
input HREADY,
input [31:0] HRDATA,


output reg [31:0] HADDR,
output reg [31:0] HWDATA,
output reg HWRITE,
output reg [1:0] HTRANS


);


reg [2:0] count;
reg phase; // 0 = write, 1 = read

always @(posedge HCLK or negedge HRESETn) begin
    if (!HRESETn) begin
        HADDR  <= 0;
        HWDATA <= 32'h11111111;
        HWRITE <= 0;
        HTRANS <= 2'b00;
        count  <= 0;
        phase  <= 0;
    end else begin

        // ---------------- WRITE BURST ----------------
        if (phase == 0) begin
            if (count == 0) begin
                HADDR  <= 32'h00000000;
                HWRITE <= 1;
                HTRANS <= 2'b10; // NONSEQ
                count  <= 1;
            end
            else if (count < 4) begin
                HADDR  <= HADDR + 4;
                HWDATA <= HWDATA + 1;
                HTRANS <= 2'b11; // SEQ
                count  <= count + 1;
            end
            else begin
                // switch to read
                count  <= 0;
                phase  <= 1;
                HTRANS <= 2'b00;
            end
        end

        // ---------------- READ BURST ----------------
        else begin
            if (count == 0) begin
                HADDR  <= 32'h00000000;
                HWRITE <= 0; // READ
                HTRANS <= 2'b10; // NONSEQ
                count  <= 1;
            end
            else if (count < 4) begin
                HADDR  <= HADDR + 4;
                HTRANS <= 2'b11; // SEQ
                count  <= count + 1;
            end
            else begin
                HTRANS <= 2'b00; // IDLE
            end
        end

    end
end


endmodule

ahb_top.v
module ahb_top(
input HCLK,
input HRESETn
);


// Master signals
wire [31:0] HADDR;
wire [31:0] HWDATA;
wire [31:0] HRDATA;
wire HWRITE;
wire HREADY;
wire [1:0] HTRANS;

// Slave signals
wire [31:0] HRDATA1, HRDATA2;
wire HREADY1, HREADY2;
wire HSEL1, HSEL2;

// -------------------------
// Address Decoder
// -------------------------
assign HSEL1 = (HADDR < 32'h00000100);
assign HSEL2 = (HADDR >= 32'h00000100);

// -------------------------
// MASTER
// -------------------------
ahb_master master(
    .HCLK(HCLK),
    .HRESETn(HRESETn),
    .HREADY(HREADY),
    .HRDATA(HRDATA),
    .HADDR(HADDR),
    .HWDATA(HWDATA),
    .HWRITE(HWRITE),
    .HTRANS(HTRANS)
);

// -------------------------
// SLAVE 1
// -------------------------
ahb_slave slave1(
    .HCLK(HCLK),
    .HRESETn(HRESETn),
    .HADDR(HADDR),
    .HWDATA(HWDATA),
    .HWRITE(HWRITE),
    .HSEL(HSEL1),
    .HRDATA(HRDATA1),
    .HREADY(HREADY1)
);

// -------------------------
// SLAVE 2
// -------------------------
ahb_slave slave2(
    .HCLK(HCLK),
    .HRESETn(HRESETn),
    .HADDR(HADDR),
    .HWDATA(HWDATA),
    .HWRITE(HWRITE),
    .HSEL(HSEL2),
    .HRDATA(HRDATA2),
    .HREADY(HREADY2)
);

// -------------------------
// MUX (Select active slave)
// -------------------------
assign HRDATA = (HSEL1) ? HRDATA1 : HRDATA2;
assign HREADY = HREADY1 | HREADY2;


endmodule

tb_ahb.v
module tb_ahb;

reg HCLK;
reg HRESETn;

// Instantiate TOP with proper connections
ahb_top uut(
    .HCLK(HCLK),
    .HRESETn(HRESETn)
);

// 🔁 Clock Generation (10 time unit period)
initial begin
    HCLK = 0;
    forever #5 HCLK = ~HCLK;
end

// 🔄 Reset + Simulation Control
initial begin
    HRESETn = 0;     // Apply reset
    #10 HRESETn = 1; // Release reset

    #100 $finish;    // End simulation
end

// 📊 Dump file for GTKWave
initial begin
    $dumpfile("ahb.vcd");
    $dumpvars(0, tb_ahb);
end

endmodule

ahb.vcd
$date
	Mon Apr 13 10:46:13 2026
$end
$version
	Icarus Verilog
$end
$timescale
	1s
$end
$scope module tb_ahb $end
$var reg 1 ! HCLK $end
$var reg 1 " HRESETn $end
$scope module uut $end
$var wire 1 ! HCLK $end
$var wire 1 # HREADY $end
$var wire 1 " HRESETn $end
$var wire 1 $ HWRITE $end
$var wire 32 % HWDATA [31:0] $end
$var wire 2 & HTRANS [1:0] $end
$var wire 1 ' HSEL2 $end
$var wire 1 ( HSEL1 $end
$var wire 1 ) HREADY2 $end
$var wire 1 * HREADY1 $end
$var wire 32 + HRDATA2 [31:0] $end
$var wire 32 , HRDATA1 [31:0] $end
$var wire 32 - HRDATA [31:0] $end
$var wire 32 . HADDR [31:0] $end
$scope module master $end
$var wire 1 ! HCLK $end
$var wire 32 / HRDATA [31:0] $end
$var wire 1 # HREADY $end
$var wire 1 " HRESETn $end
$var reg 32 0 HADDR [31:0] $end
$var reg 2 1 HTRANS [1:0] $end
$var reg 32 2 HWDATA [31:0] $end
$var reg 1 $ HWRITE $end
$var reg 3 3 count [2:0] $end
$var reg 1 4 phase $end
$upscope $end
$scope module slave1 $end
$var wire 32 5 HADDR [31:0] $end
$var wire 1 ! HCLK $end
$var wire 1 " HRESETn $end
$var wire 1 ( HSEL $end
$var wire 32 6 HWDATA [31:0] $end
$var wire 1 $ HWRITE $end
$var reg 32 7 HRDATA [31:0] $end
$var reg 1 * HREADY $end
$var integer 32 8 i [31:0] $end
$upscope $end
$scope module slave2 $end
$var wire 32 9 HADDR [31:0] $end
$var wire 1 ! HCLK $end
$var wire 1 " HRESETn $end
$var wire 1 ' HSEL $end
$var wire 32 : HWDATA [31:0] $end
$var wire 1 $ HWRITE $end
$var reg 32 ; HRDATA [31:0] $end
$var reg 1 ) HREADY $end
$var integer 32 < i [31:0] $end
$upscope $end
$upscope $end
$upscope $end
$enddefinitions $end
#0
$dumpvars
b100000000 <
b0 ;
b10001000100010001000100010001 :
b0 9
b100000000 8
b0 7
b10001000100010001000100010001 6
b0 5
04
b0 3
b10001000100010001000100010001 2
b0 1
b0 0
b0 /
b0 .
b0 -
b0 ,
b0 +
1*
1)
1(
0'
b0 &
b10001000100010001000100010001 %
0$
1#
0"
0!
$end
#5
1!
#10
0!
1"
#15
b1 3
b10 &
b10 1
1$
1!
#20
0!
#25
b10 3
b11 &
b11 1
b10001000100010001000100010010 %
b10001000100010001000100010010 2
b10001000100010001000100010010 6
b10001000100010001000100010010 :
b100 .
b100 0
b100 5
b100 9
1!
#30
0!
#35
b11 3
b10001000100010001000100010011 %
b10001000100010001000100010011 2
b10001000100010001000100010011 6
b10001000100010001000100010011 :
b1000 .
b1000 0
b1000 5
b1000 9
1!
#40
0!
#45
b100 3
b10001000100010001000100010100 %
b10001000100010001000100010100 2
b10001000100010001000100010100 6
b10001000100010001000100010100 :
b1100 .
b1100 0
b1100 5
b1100 9
1!
#50
0!
#55
b0 &
b0 1
14
b0 3
1!
#60
0!
#65
b1 3
b10 &
b10 1
0$
b0 .
b0 0
b0 5
b0 9
1!
#70
0!
#75
b10001000100010001000100010001 -
b10001000100010001000100010001 /
b10 3
b11 &
b11 1
b100 .
b100 0
b100 5
b100 9
b10001000100010001000100010001 ,
b10001000100010001000100010001 7
1!
#80
0!
#85
b10001000100010001000100010010 -
b10001000100010001000100010010 /
b10001000100010001000100010010 ,
b10001000100010001000100010010 7
b11 3
b1000 .
b1000 0
b1000 5
b1000 9
1!
#90
0!
#95
b10001000100010001000100010011 -
b10001000100010001000100010011 /
b100 3
b1100 .
b1100 0
b1100 5
b1100 9
b10001000100010001000100010011 ,
b10001000100010001000100010011 7
1!
#100
0!
#105
b10001000100010001000100010100 -
b10001000100010001000100010100 /
b10001000100010001000100010100 ,
b10001000100010001000100010100 7
b0 &
b0 1
1!
